{"currencies": [
  {"code": "UNC",  "name": "UN Credits",       "source": "Altered Carbon",                      "rate": 1},
  {"code": "REP",  "name": "Republic Credits",  "source": "Star Wars",                           "rate": 3},
  {"code": "LAT",  "name": "Latinum",            "source": "Star Trek",                           "rate": 4},
  {"code": "QUA",  "name": "Quatloos",           "source": "Star Trek",                           "rate": 11},
  {"code": "NIN",  "name": "Ning",               "source": "The Hitchhiker's Guide to the Galaxy", "rate": 13},
  {"code": "BZD",  "name": "Buckazoid",          "source": "Futurama",                            "rate": 15},
  {"code": "COIN", "name": "Coin",               "source": "Cyberpunk Sci-Fi",                    "rate": 25},
  {"code": "TKN",  "name": "Token",              "source": "Cyberpunk Sci-Fi",                    "rate": 30}
]}
